{"openapi":"3.0.1","info":{"title":"SpringShop API","description":"Spring shop sample application","license":{"name":"Apache 2.0","url":"http://springdoc.org"},"version":"v0.0.1"},"externalDocs":{"description":"SpringShop Wiki Documentation","url":"https://springshop.wiki.github.org/docs"},"servers":[{"url":"http://localhost:8080","description":"Generated server url"}],"paths":{"/users":{"get":{"tags":["users"],"summary":"User Details","description":"Returns the list of the users","operationId":"getAllUsers","responses":{"200":{"description":"List of the users","content":{"application/json":{"schema":{"type":"array","items":{"$ref":"#/components/schemas/UserDto"}}}}}}},"post":{"tags":["users"],"summary":"Create user","description":"Creates a new user ","operationId":"createUser","requestBody":{"content":{"application/json":{"schema":{"$ref":"#/components/schemas/UserDto"}}},"required":true},"responses":{"201":{"description":"The newly created user.","content":{"application/json":{"schema":{"$ref":"#/components/schemas/UserDto"}}}}}}},"/todos":{"get":{"tags":["todos"],"summary":"Todo Details","description":"Returns the list of the Todos","operationId":"getAllTodos","responses":{"200":{"description":"List of the Todos","content":{"application/json":{"schema":{"type":"array","items":{"$ref":"#/components/schemas/TodoDto"}}}}}}},"post":{"tags":["todos"],"summary":"Create To do","description":"Creates a new to do ","operationId":"createTodo","requestBody":{"content":{"application/json":{"schema":{"$ref":"#/components/schemas/TodoDto"}}},"required":true},"responses":{"201":{"description":"The newly created To do.","content":{"application/json":{"schema":{"$ref":"#/components/schemas/TodoDto"}}}}}}},"/categories":{"get":{"tags":["categories"],"summary":"Category Details","description":"Returns the list of the categories","operationId":"getAllCategories","responses":{"200":{"description":"List of the categories","content":{"application/json":{"schema":{"type":"array","items":{"$ref":"#/components/schemas/CategoryDto"}}}}}}},"post":{"tags":["categories"],"summary":"Create category","description":"Creates a new category ","operationId":"createCategory","requestBody":{"content":{"application/json":{"schema":{"$ref":"#/components/schemas/CategoryDto"}}},"required":true},"responses":{"201":{"description":"The newly created Category.","content":{"application/json":{"schema":{"$ref":"#/components/schemas/CategoryDto"}}}}}}},"/auth/login":{"post":{"tags":["auth"],"summary":"Login user","description":"Creates a new user ","operationId":"loginUser","requestBody":{"content":{"application/json":{"schema":{"$ref":"#/components/schemas/UserDto"}}},"required":true},"responses":{"201":{"description":"The connected user.","content":{"application/json":{"schema":{"$ref":"#/components/schemas/UserDto"}}}}}}},"/users/{id}":{"get":{"tags":["users"],"summary":"User Details","description":"Returns the list of the users","operationId":"getUser","parameters":[{"name":"The use id","in":"path","required":true,"schema":{"type":"integer","format":"int64"}}],"responses":{"200":{"description":"The user","content":{"application/json":{"schema":{"$ref":"#/components/schemas/UserDto"}}}},"404":{"description":"User not found","content":{"application/json":{"schema":{"$ref":"#/components/schemas/UserDto"}}}}}},"delete":{"tags":["users"],"summary":"Delete a user","description":"Deletes a user by ID","operationId":"deleteUser","parameters":[{"name":"The use id","in":"path","required":true,"schema":{"type":"integer","format":"int64"}}],"responses":{"200":{"description":"The user","content":{"*/*":{"schema":{"type":"object"}}}},"404":{"description":"User not found","content":{"*/*":{"schema":{"type":"object"}}}}}},"patch":{"tags":["users"],"summary":"Update user","description":"Updates an existing user ","operationId":"updateUser","parameters":[{"name":"User ID","in":"path","required":true,"schema":{"type":"integer","format":"int64"}}],"requestBody":{"content":{"application/json":{"schema":{"$ref":"#/components/schemas/UserDto"}}},"required":true},"responses":{"201":{"description":"The newly created user.","content":{"application/json":{"schema":{"$ref":"#/components/schemas/UserDto"}}}}}}},"/todos/{id}":{"get":{"tags":["todos"],"summary":"Todo Details","description":"Returns the Todo","operationId":"getTodo","parameters":[{"name":"id","in":"path","description":"The Todo Id","required":true,"schema":{"type":"integer","format":"int64"}}],"responses":{"404":{"description":"Todo not found","content":{"application/json":{"schema":{"$ref":"#/components/schemas/TodoDto"}}}},"200":{"description":"The Todo","content":{"application/json":{"schema":{"$ref":"#/components/schemas/TodoDto"}}}}}},"delete":{"tags":["todos"],"summary":"Delete Todo","description":"Deletes a Todo by ID","operationId":"deleteTodo","parameters":[{"name":"id","in":"path","description":"The Todo id","required":true,"schema":{"type":"integer","format":"int64"}}],"responses":{"404":{"description":"Todo not found","content":{"*/*":{"schema":{"type":"string"}}}},"200":{"description":"The Todo deleted","content":{"*/*":{"schema":{"type":"string"}}}}}},"patch":{"tags":["todos"],"summary":"Update Todo","description":"Updates an existing Todo","operationId":"updateTodo","parameters":[{"name":"id","in":"path","description":"The Todo Id","required":true,"schema":{"type":"integer","format":"int64"}}],"requestBody":{"content":{"application/json":{"schema":{"$ref":"#/components/schemas/TodoDto"}}},"required":true},"responses":{"201":{"description":"The newly created Todo.","content":{"application/json":{"schema":{"$ref":"#/components/schemas/TodoDto"}}}}}}},"/categories/{id}":{"get":{"tags":["categories"],"summary":"Category Details","description":"Returns the list of the users","operationId":"getCategory","parameters":[{"name":"The category id","in":"path","required":true,"schema":{"type":"integer","format":"int64"}}],"responses":{"200":{"description":"The Category","content":{"application/json":{"schema":{"$ref":"#/components/schemas/CategoryDto"}}}},"404":{"description":"Category not found","content":{"application/json":{"schema":{"$ref":"#/components/schemas/CategoryDto"}}}}}},"delete":{"tags":["categories"],"summary":"Delete category","description":"Deletes a category by ID","operationId":"deleteCategory","parameters":[{"name":"The category id","in":"path","required":true,"schema":{"type":"integer","format":"int64"}}],"responses":{"404":{"description":"Category not found","content":{"*/*":{"schema":{"type":"string"}}}},"200":{"description":"The category deleted","content":{"*/*":{"schema":{"type":"string"}}}}}},"patch":{"tags":["categories"],"summary":"Update Category","description":"Updates an existing Category ","operationId":"updateCategory","parameters":[{"name":"id","in":"path","description":"The Todo Id","required":true,"schema":{"type":"integer","format":"int64"}}],"requestBody":{"content":{"application/json":{"schema":{"$ref":"#/components/schemas/CategoryDto"}}},"required":true},"responses":{"201":{"description":"The newly created user.","content":{"application/json":{"schema":{"$ref":"#/components/schemas/CategoryDto"}}}}}}},"/categories/users/{userId}":{"get":{"tags":["categories"],"summary":"Category Details by user ID","description":"Returns the list of the categories of a selected user","operationId":"getAllCategoriesByUserId","parameters":[{"name":"User ID","in":"path","required":true,"schema":{"type":"integer","format":"int64"}}],"responses":{"200":{"description":"List of the categories","content":{"application/json":{"schema":{"type":"array","items":{"$ref":"#/components/schemas/CategoryDto"}}}}}}}},"/categories/todos/{id}":{"get":{"tags":["categories"],"summary":"Todo Details by category ID","description":"Returns the list of the Todo of a selected category","operationId":"getAllTodoByCategoriesId","parameters":[{"name":"Category ID","in":"path","required":true,"schema":{"type":"integer","format":"int64"}}],"responses":{"200":{"description":"List of the Todos","content":{"application/json":{"schema":{"type":"array","items":{"$ref":"#/components/schemas/TodoDto"}}}}}}}},"/categories/todos/today/{userId}":{"get":{"tags":["categories"],"summary":"List of all categories and Todo for today","description":"Returns the list of the Todo of a selected category","operationId":"getAllTodoByCategoriesForToday","parameters":[{"name":"User ID","in":"path","required":true,"schema":{"type":"integer","format":"int64"}}],"responses":{"200":{"description":"List of the Todos","content":{"application/json":{"schema":{"type":"array","items":{"$ref":"#/components/schemas/TodoDto"}}}}}}}}},"components":{"schemas":{"UserDto":{"type":"object","properties":{"id":{"type":"integer","format":"int64"},"firstName":{"type":"string"},"lastName":{"type":"string"},"email":{"type":"string"},"userName":{"type":"string"},"password":{"type":"string"}}},"CategoryDto":{"type":"object","properties":{"id":{"type":"integer","format":"int64"},"name":{"type":"string"},"description":{"type":"string"},"user":{"$ref":"#/components/schemas/UserDto"},"todoList":{"type":"array","items":{"$ref":"#/components/schemas/TodoDto"}}}},"TodoDto":{"type":"object","properties":{"id":{"type":"integer","format":"int64"},"title":{"type":"string"},"description":{"type":"string"},"startDate":{"type":"string","format":"date-time"},"done":{"type":"boolean"},"favorite":{"type":"boolean"},"category":{"$ref":"#/components/schemas/CategoryDto"}}}}}}